<?xml version="1.0" encoding="utf-8" ?>
<dwsync>
<file name="divreplace.html" server="frogss.pl//domains/frogss.pl/public_html/mvc/" local="130471455233606607" remote="130288536000000000" Dst="2" />
<file name="inlinetextarea.html" server="frogss.pl//domains/frogss.pl/public_html/mvc/" local="130471455237337029" remote="130288536000000000" Dst="2" />
<file name="jquery.html" server="frogss.pl//domains/frogss.pl/public_html/mvc/" local="130471455237907099" remote="130288536000000000" Dst="2" />
<file name="readonly.html" server="frogss.pl//domains/frogss.pl/public_html/mvc/" local="130471455278722239" remote="130288536000000000" Dst="2" />
<file name="replacebyclass.html" server="frogss.pl//domains/frogss.pl/public_html/mvc/" local="130471455279752698" remote="130288536000000000" Dst="2" />
<file name="appendto.html" server="frogss.pl//domains/frogss.pl/public_html/mvc/" local="130471455338060033" remote="130288536000000000" Dst="2" />
<file name="xhtmlstyle.html" server="frogss.pl//domains/frogss.pl/public_html/mvc/" local="130471455342140542" remote="130288536000000000" Dst="2" />
<file name="datafiltering.html" server="frogss.pl//domains/frogss.pl/public_html/mvc/" local="130471455356472345" remote="130288536000000000" Dst="2" />
<file name="inlinebycode.html" server="frogss.pl//domains/frogss.pl/public_html/mvc/" local="130471455357412455" remote="130288536000000000" Dst="2" />
</dwsync>